bacorakel/__init__.py
bacorakel/assets/custom.css
bacorakel/cli.py
bacorakel/controller.py
bacorakel/dashboard.py
bacorakel/logging.py
bacorakel/mockup.py
bacorakel/myweigh.py
bacorakel/state.py
bacorakel-0.56.3.dist-info/entry_points.txt
bacorakel-0.56.3.dist-info/WHEEL
bacorakel-0.56.3.dist-info/METADATA
bacorakel-0.56.3.dist-info/RECORD
